agently_workflow/LICENSE
agently_workflow/MainExecutor.py
agently_workflow/README.md
agently_workflow/Schema.py
agently_workflow/Workflow.py
agently_workflow/__init__.py
agently_workflow/_global.py
agently_workflow/global_plugin_manager.py
agently_workflow/Chunk/Condition.py
agently_workflow/Chunk/Loop.py
agently_workflow/Chunk/__init__.py
agently_workflow/Chunk/helper.py
agently_workflow/Runtime/BranchState.py
agently_workflow/Runtime/Checkpoint.py
agently_workflow/Runtime/Repository.py
agently_workflow/Runtime/Snapshot.py
agently_workflow/Runtime/State.py
agently_workflow/Runtime/__init__.py
agently_workflow/custom_types/__init__.py
agently_workflow/custom_types/chunk_data.py
agently_workflow/executors/__init__.py
agently_workflow/executors/builtin/ConditionExecutor.py
agently_workflow/executors/builtin/EndExecutor.py
agently_workflow/executors/builtin/StartExecutor.py
agently_workflow/executors/builtin/__init__.py
agently_workflow/executors/builtin/install.py
agently_workflow/executors/generater/__init__.py
agently_workflow/executors/generater/loop.py
agently_workflow/lib/BreakingHub.py
agently_workflow/lib/ChunkExecutorManager.py
agently_workflow/lib/Store.py
agently_workflow/lib/__init__.py
agently_workflow/lib/constants.py
agently_workflow/lib/painter.py
agently_workflow/plugins/__init__.py
agently_workflow/plugins/storage/FileStorage.py
agently_workflow/plugins/storage/SQLite.py
agently_workflow/plugins/storage/__init__.py
agently_workflow/plugins/storage/utils/StorageABC.py
agently_workflow/plugins/storage/utils/__init__.py
agently_workflow/utils/DataOps.py
agently_workflow/utils/IdGenerator.py
agently_workflow/utils/PluginManager.py
agently_workflow/utils/RuntimeCtx.py
agently_workflow/utils/StorageDelegate.py
agently_workflow/utils/ToolManager.py
agently_workflow/utils/__init__.py
agently_workflow/utils/chunk_helper.py
agently_workflow/utils/exec_tree.py
agently_workflow/utils/find.py
agently_workflow/utils/load_json.py
agently_workflow/utils/logger.py
agently_workflow-0.1.3.dist-info/METADATA
agently_workflow-0.1.3.dist-info/WHEEL
agently_workflow-0.1.3.dist-info/top_level.txt
agently_workflow-0.1.3.dist-info/RECORD
