Metadata-Version: 2.1
Name: agently_workflow
Version: 0.1.3
Summary: A standalone workflow spun off from [Agently](https://github.com/Maplemx/Agently), featuring minimal third-party dependencies (e.g., json5).
Author-email: sunjingji <sunjingji@qq.com>
License:                                  Apache License
Keywords: workflow,agently,automation minimal third-party dependencies
Requires-Python: >=3.8
Requires-Dist: json5>=0.10.0
